table_enforcer/__init__.py
table_enforcer/errors.py
table_enforcer/main_classes.py
table_enforcer/utils/__init__.py
table_enforcer/utils/recode/__init__.py
table_enforcer/utils/recode/decorators.py
table_enforcer/utils/recode/funcs.py
table_enforcer/utils/validate/__init__.py
table_enforcer/utils/validate/decorators.py
table_enforcer/utils/validate/funcs.py
table_enforcer-0.4.4.dist-info/DESCRIPTION.rst
table_enforcer-0.4.4.dist-info/METADATA
table_enforcer-0.4.4.dist-info/RECORD
table_enforcer-0.4.4.dist-info/WHEEL
table_enforcer-0.4.4.dist-info/metadata.json
table_enforcer-0.4.4.dist-info/top_level.txt
tests/Usage_Demo.py
tests/__init__.py
tests/conftest.py
tests/test_MTOColumn.py
tests/test_OTMColumn.py
tests/test_column.py
tests/test_enforcer.py
tests/test_imports.py
tests/test_table_enforcer.py
tests/files/demo_table.csv
tests/files/demo_table_bad.csv
tests/files/test_OTMColumn.csv
