Metadata-Version: 2.0
Name: table-enforcer
Version: 0.4.4
Summary: ORM-like package for defining, loading, and validating table schemas in pandas.
Home-page: https://github.com/xguse/table_enforcer
Author: Gus Dunn
Author-email: w.gus.dunn@gmail.com
License: MIT license
Keywords: table_enforcer
Platform: UNKNOWN
Classifier: Development Status :: 2 - Pre-Alpha
Classifier: Intended Audience :: Developers
Classifier: License :: OSI Approved :: MIT License
Classifier: Natural Language :: English
Classifier: Programming Language :: Python :: 3.5
Classifier: Programming Language :: Python :: 3.6
Requires-Dist: python-box
Requires-Dist: munch
Requires-Dist: xlrd
Requires-Dist: xlwt
Requires-Dist: logzero
Requires-Dist: numpy
Requires-Dist: numexpr
Requires-Dist: pandas
